[{
  "callout": "We need food",
  "active": "true",
  "list": [
    {
      "name": "salami",
      "total": "20",
      "received": "10",
      "done": "false",
      "url": "https://www.amazon.com/Molinari-Sons-Francisco-Italian-Wrapped/dp/B00H4GXO24/ref=sr_1_4_a_it?ie=UTF8&qid=1508514128&sr=8-4&keywords=salami"
    },
    {
      "name": "beef",
      "total": "10",
      "received": "1",
      "done": "false",
      "url": "https://www.amazon.com/H-F-s-Outstanding-Black-Angus-T-Bone/dp/B0199STNS8/ref=sr_1_7_s_it?s=grocery&ie=UTF8&qid=1508514175&sr=1-7&keywords=beef&th=1"
    },
    {
      "name": "slim jims",
      "total": "1000",
      "received": "432",
      "done": "false",
      "url": "https://www.amazon.com/Slim-Jim-Smoked-Snacks-Original/dp/B00HDC09OA/ref=sr_1_6_s_it?s=grocery&ie=UTF8&qid=1508514203&sr=1-6&keywords=slim%2Bjim&th=1"
    }
  ]
}]
